simplecheck
