Metadata-Version: 2.1
Name: simplecheck
Version: 0.0.4
Summary: A python program to check all data in a program more easily
Home-page: https://github.com/Yicas-3111/Ez_Check
Author: Yicas-3111
Author-email: 2556152782@qq.com
License: UNKNOWN
Platform: UNKNOWN
Classifier: Programming Language :: Python :: 3
Classifier: License :: OSI Approved :: MIT License
Classifier: Operating System :: OS Independent
